{
  "analytics": {
    "attributes": "Özellikler",
    "avgXG": "Ort. xG",
    "belowAvg": "Altı",
    "elite": "Elit",
    "good": "İyi",
    "leagueAverage": "Lig Ortalaması",
    "leagueComparison": "Lig Karşılaştırması",
    "leagueComparisonDescription": "Lig oyuncularıyla karşılaştırmalı performans",
    "overall": "Genel",
    "shotMap": "Şut Haritası",
    "shotMapDescription": "Maçlardaki şut konumları",
    "shotsLabel": "Şutlar"
  },
  "careerStats": {
    "accurateCrosses": "İsabetli Ortalar",
    "accurateLongBalls": "İsabetli Uzun Toplar",
    "accurateThroughBalls": "İsabetli Ara Paslar",
    "aerialDuelsWon": "Kazanılan Hava Mücadeleleri",
    "attacking": "Hücum",
    "ballRecoveriesInAttack": "Hücumda Kurtarmalar",
    "ballRecoveriesPerGame": "Maç Başı Kurtarma",
    "bigChancesCreated": "Yaratılan Büyük Fırsatlar",
    "bigChancesMissed": "Kaçırılan Büyük Fırsatlar",
    "clearancesPerGame": "Maç Başı Uzaklaştırma",
    "defending": "Savunma",
    "directFreeKickEffectiveness": "Direkt SV Etkinliği",
    "discipline": "Disiplin",
    "dribbledPastPerGame": "Maç Başı Geçilme",
    "duels": "Düellolar",
    "duelsWon": "Kazanılan İkili Mücadeleler",
    "errorsLeadingToGoal": "Gole Yol Açan Hatalar",
    "errorsLeadingToShot": "Şuta Yol Açan Hatalar",
    "expectedAssists": "Beklenen Asistler (xA)",
    "foulsDrawn": "Kazanılan Fauller",
    "foulsPerGame": "Maç Başı Faul",
    "freeKickGoals": "Serbest Vuruş Golleri",
    "general": "Genel",
    "goalsFromInsideBox": "Ceza Sahası İçi Goller",
    "goalsFromOutsideBox": "Ceza Sahası Dışı Goller",
    "groundDuelsWon": "Kazanılan Yer Mücadeleleri",
    "headedGoals": "Kafa Golleri",
    "interceptions": "Top Kesme",
    "keyPasses": "Kilit Paslar",
    "leftFootGoals": "Sol Ayak Golleri",
    "noStatsAvailable": "Bu seçim için istatistik yok.",
    "offsides": "Ofsaytlar",
    "passesInFinalThird": "Son Üçlüde Paslar",
    "passesInOwnHalf": "Kendi Yarısında Paslar",
    "passing": "Pas ve Yaratıcılık",
    "penaltiesConceded": "Verilen Penaltılar",
    "penaltiesWon": "Kazanılan Penaltılar",
    "playMoreMatches": "Kariyer istatistiklerini görmek için daha fazla maç oyna",
    "possessionLost": "Kaybedilen Toplar",
    "redCards": "Kırmızı Kartlar",
    "redCardsFromSecondYellow": "Kırmızı Kartlar (2. Sarı)",
    "rightFootGoals": "Sağ Ayak Golleri",
    "shotsBlockedPerGame": "Maç Başı Engellenen Şut",
    "successfulDribbles": "Başarılı Driblingler",
    "tacklesPerGame": "Maç Başı Müdahale",
    "touches": "Top Temasları",
    "yellowCards": "Sarı Kartlar"
  },
  "detailedStats": {
    "acc": "isb.",
    "accurateCrosses": "İsabetli Ortalar",
    "accurateLongBalls": "İsabetli Uzun Toplar",
    "accurateThroughBalls": "İsabetli Ara Paslar",
    "aerialDuels": "Hava Düelloları",
    "aerialDuelsTitle": "Hava Düelloları",
    "aerialDuelsWonPercentage": "Kazanılan Hava Düelloları %",
    "allDuels": "Tüm Düellolar",
    "assists": "Asistler",
    "assistsPerMatch": "Maç Başı Asist",
    "attacking": "Hücum",
    "averageRating": "Ortalama Puan",
    "avgRating": "Ort. Puan",
    "backwardPasses": "Geri Paslar",
    "ballRecoveries": "Top Kurtarma",
    "ballRecovery": "Top Kurtarma",
    "ballTouchesPerGame": "Maç Başı Top Teması",
    "bigChances": "Büyük Fırsatlar",
    "bigChancesConverted": "Dönüştürülen Büyük Fırsatlar",
    "bigChancesCreated": "Yaratılan Büyük Fırsatlar",
    "bigChancesMissed": "Kaçırılan Büyük Fırsatlar",
    "blocks": "Bloklar",
    "blocksPerGame": "Maç Başı Blok",
    "braces": "Çiftler",
    "carriesIntoFinalThird": "Son üçlüye taşımalar",
    "carriesIntoPenArea": "Ceza sahasına taşımalar",
    "chipGoals": "Aşırtma Golleri",
    "chipShots": "Aşırtmalar",
    "cleanSheetPercentage": "Gol Yememe %",
    "cleanSheets": "Gol Yemeden",
    "clearances": "Uzaklaştırmalar",
    "clearancesPerGame": "Maç Başı Uzaklaştırma",
    "completed": "tamamlandı",
    "conv": "dön.",
    "cornerAccuracy": "Köşe Vuruşu İsabeti %",
    "cornersTaken": "Kullanılan Köşe Vuruşları",
    "creativityPassing": "Yaratıcılık ve Pas",
    "crossAccuracy": "Orta İsabeti %",
    "crosses": "Ortalar",
    "crossesClaimed": "Alınan Ortalar",
    "curvedGoals": "Kıvrımlı Şutlar",
    "curvedShots": "Kıvrımlı Şutlar",
    "decoyRuns": "Aldatmaca koşular",
    "defending": "Savunma",
    "defensiveRuns": "Savunma Koşuları",
    "directFKEffectiveness": "Direkt SV Etkinliği",
    "discipline": "Disiplin",
    "disciplineTitle": "Disiplin",
    "distance": "Mesafe",
    "distanceCovered": "Kat Edilen Mesafe (km)",
    "distributionAccuracy": "Dağıtım İsabeti",
    "dribbleSuccess": "Dribling Başarısı %",
    "dribbledPast": "Geçildi",
    "dribbledPastDefThird": "Geçildi (sav. üçlüsü)",
    "dribbledPastInDefensiveThird": "Savunma Üçlüsünde Geçilme",
    "dribbledPastPerGame": "Maç Başı Geçilme",
    "dribblesAttempted": "Denenen Driblingler",
    "dribblesSucceeded": "Başarılı Driblingler",
    "dribblingBallControl": "Dribling ve Top Kontrolü",
    "duelsContests": "Düellolar ve Mücadeleler",
    "duelsWonPercentage": "Kazanılan Düellolar %",
    "errorsAndMistakesTitle": "Hatalar",
    "errorsLeadingToGoal": "Gole Yol Açan Hatalar",
    "errorsLeadingToShot": "Şuta Yol Açan Hatalar",
    "errorsMistakes": "Hatalar",
    "errorsToGoal": "Hatalar → gol",
    "errorsToShot": "Hatalar → şut",
    "expectedAssists": "Beklenen Asistler (xA)",
    "expectedGoals": "Beklenen Goller (xG)",
    "expectedGoalsConceded": "Beklenen Yenen Goller (xGC)",
    "finalThird": "Son üçlü",
    "firstTouchSuccess": "İlk Dokunuş Başarısı %",
    "forwardPasses": "İleri Paslar",
    "forwardPassesCompleted": "Tamamlanan İleri Paslar",
    "foulsCommitted": "Yapılan Fauller",
    "foulsDrawn": "Kazanılan Fauller",
    "foulsDrawnPerGame": "Maç Başı Kazanılan Faul",
    "foulsPerGame": "Maç Başı Faul",
    "freeKickGoals": "Serbest Vuruş Golleri",
    "freeKicks": "Serbest Vuruşlar",
    "gamesAsSubstitute": "Yedek Oynadığı Maçlar",
    "gamesStarted": "Başladığı Maçlar",
    "generalStats": "Genel İstatistikler",
    "gkDistribution": "Kaleci Dağıtımı ve Aksiyonları",
    "goalConversion": "Gol Dönüşümü",
    "goalCreatingActions": "Gol yaratan aksiyonlar",
    "goalTypes": "Gol Türleri",
    "goalkeeping": "Kalecilik",
    "goals": "Goller",
    "goalsByType": "Türe Göre Goller",
    "goalsConceded": "Yenen Goller",
    "goalsConcededPerGame": "Maç Başı Yenen Gol",
    "goalsFromInsideBox": "Ceza Sahası İçi Goller",
    "goalsFromOutsideBox": "Ceza Sahası Dışı Goller",
    "goalsPerMatch": "Maç Başı Gol",
    "goalsPreventedVsExpected": "Önlenen Goller vs Beklenen",
    "groundDuels": "Yer Düelloları",
    "groundDuelsTitle": "Yer Düelloları",
    "groundDuelsWonPercentage": "Kazanılan Yer Düelloları %",
    "hatTricks": "Hat-trickler",
    "headedClearances": "Kafa ile Uzaklaştırmalar",
    "headedGoals": "Kafa Golleri",
    "headers": "Kafalar",
    "headersWon": "Kazanılan Kafalar",
    "headersWonPercentage": "Kazanılan Kafalar %",
    "highIntensityRuns": "Yüksek Yoğunluklu Koşular",
    "inAttack": "Hücumda",
    "inBox": "ceza sahasında",
    "inDefence": "Savunmada",
    "inMidfield": "Orta sahada",
    "insideBox": "Ceza sahası içi",
    "interceptions": "Top Kesme",
    "interceptionsPerGame": "Maç Başı Top Kesme",
    "intoPenaltyArea": "Ceza sahasına",
    "keyPasses": "Kilit Paslar",
    "keyPassesPerGame": "Maç Başı Kilit Pas",
    "kmCovered": "km kat edildi",
    "lastManTackles": "Son Adam Müdahaleleri",
    "leftFoot": "Sol ayak",
    "leftFootGoals": "Sol Ayak Golleri",
    "longBallAccuracy": "Uzun Top İsabeti %",
    "longBalls": "Uzun Toplar",
    "longThrows": "Uzun atışlar",
    "lostInOwnHalf": "Kendi yarısında kayıp",
    "manOfTheMatch": "Maçın Adamı",
    "matchEventsAchievements": "Maç Olayları ve Başarılar",
    "matches": "Maçlar",
    "matchesAsCaptain": "Kaptan olarak maçlar",
    "matchesPlayed": "Oynanan Maçlar",
    "meters": "metre",
    "minutes": "Dakikalar",
    "minutesPlayed": "Oynanan Dakikalar",
    "missed": "kaçırılan",
    "noEventsRecorded": "Bu sezon kayıtlı olay yok.",
    "noStatsAvailable": "Bu sezon için detaylı istatistik yok.",
    "nutmegs": "Bacak Arası",
    "offensiveRuns": "Hücum Koşuları",
    "offsides": "Ofsaytlar",
    "offsidesPerGame": "Maç Başı Ofsayt",
    "onTarget": "isabetli",
    "oneVsOneWon": "1v1 kazandı",
    "oppositionHalf": "Rakip yarısı",
    "outOfPosition": "Pozisyon Dışı",
    "outsideBox": "Ceza sahası dışı",
    "overallWinRate": "Toplam Galibiyet Oranı",
    "overlappingRuns": "Bindirmeli koşular",
    "ownGoals": "Kendi Kalesine Goller",
    "ownHalf": "Kendi yarısı",
    "passCompletion": "Pas Tamamlama %",
    "passCompletionRate": "Pas Oranı",
    "passesBlocked": "Engellenen Paslar",
    "passesCompleted": "Tamamlanan Paslar",
    "passesInFinalThird": "Son Üçlüde Paslar",
    "passesInOppositionHalf": "Rakip Yarısında Paslar",
    "passesInOwnHalf": "Kendi Yarısında Paslar",
    "passesIntercepted": "Kesilen Paslar",
    "passesPerGame": "Maç Başı Pas",
    "passingAndCreativity": "Pas ve Yaratıcılık",
    "passingDistribution": "Pas Dağılımı",
    "passingStats": "Pas İstatistikleri",
    "penalties": "Penaltılar",
    "penaltiesConceded": "Verilen Penaltılar",
    "penaltiesFaced": "Karşılaşılan Penaltılar",
    "penaltiesMissed": "Kaçırılan penaltılar",
    "penaltiesSaved": "Kurtarılan Penaltılar",
    "penaltiesWon": "Kazanılan Penaltılar",
    "penaltyConversion": "Penaltı Dönüşümü",
    "penaltyGoals": "Penaltı Golleri",
    "penaltySavePercentage": "Penaltı Kurtarma %",
    "perGame": "/maç",
    "perfectPassingGames": "Mükemmel pas maçları",
    "physicalContests": "Fiziksel Mücadeleler",
    "physicalContestsWon": "Kazanılan Fiziksel Mücadeleler",
    "possessionLost": "Kaybedilen Toplar",
    "possessionLostInOwnHalf": "Kendi Yarısında Kaybedilen Toplar",
    "pressureSuccess": "Baskı Başarısı %",
    "pressuresApplied": "Uygulanan Baskılar",
    "progressiveCarries": "İlerleyici taşımalar",
    "punchesMade": "Yapılan Yumruklar",
    "recoveriesInAttack": "Hücumda Kurtarmalar",
    "recoveriesInDefence": "Savunmada Kurtarmalar",
    "recoveriesInMidfield": "Orta Sahada Kurtarmalar",
    "recoveriesPerGame": "Maç Başı Kurtarma",
    "redCards": "Kırmızı kartlar",
    "redCardsDirect": "Kırmızı Kartlar (Direkt)",
    "redCardsSecondYellow": "Kırmızı Kartlar (2. Sarı)",
    "rightFoot": "Sağ ayak",
    "rightFootGoals": "Sağ Ayak Golleri",
    "savePercentage": "Kurtarış %",
    "saves": "Kurtarışlar",
    "savesPerGame": "Maç Başı Kurtarış",
    "secondYellowRed": "2. sarı → kırmızı",
    "shootingAndFinishing": "Şut ve Bitiricilik",
    "shotAccuracy": "Şut İsabeti",
    "shotCreatingActions": "Şut yaratan aksiyonlar",
    "shots": "Şutlar",
    "shotsBlocked": "Engellenen Şutlar",
    "shotsFaced": "Karşılaşılan şutlar",
    "shotsOffTarget": "İsabetsiz Şutlar",
    "shotsOnTarget": "İsabetli Şutlar",
    "shotsOnTargetFaced": "Karşılaşılan İsabetli Şutlar",
    "shotsOnTargetPerGame": "Maç Başı İsabetli Şut",
    "shotsPerGame": "Maç Başı Şut",
    "sidewaysPasses": "Yatay Paslar",
    "skillMoves": "Beceri hareketleri",
    "skillMovesCompleted": "Tamamlanan Beceri Hareketleri",
    "slidingTackleSuccess": "Kayarak Müdahale Başarısı %",
    "slidingTackles": "Kayarak Müdahaleler",
    "sprintDistance": "Sprint Mesafesi (km)",
    "sprintsPerGame": "Maç Başı Sprint",
    "standingTackles": "Ayakta Müdahaleler",
    "starts": "ilk 11",
    "sub": "yedek",
    "succ": "bşr.",
    "successfulDribbles": "Başarılı driblingler",
    "successfulPressures": "Başarılı baskılar",
    "supportiveRuns": "Destekleyici koşular",
    "sweeperActions": "Libero Aksiyonları",
    "sweeperClearances": "Libero uzaklaştırmaları",
    "tackleSuccess": "Müdahale Başarısı %",
    "tackles": "Müdahaleler",
    "tacklesPerGame": "Maç Başı Müdahale",
    "tacklesWon": "Kazanılan Müdahaleler",
    "teamOfTheWeek": "Haftanın Takımı",
    "teamPlayRating": "Takım oyunu puanı",
    "teamPlaySupport": "Takım Oyunu ve Destek",
    "throughBallAccuracy": "Ara Pas İsabeti",
    "throughBalls": "Ara Paslar",
    "timesDispossessed": "Top Kaybedilen Anlar",
    "timesDribbledPast": "Geçilen Anlar",
    "totalDuels": "Toplam Düellolar",
    "totalPasses": "Toplam Paslar",
    "touches": "Top Temasları",
    "touchesInOppositionBox": "Rakip Ceza Sahasında Temaslar",
    "trackingRuns": "Takip Koşuları",
    "underlappingRuns": "Alt koşular",
    "volleyGoals": "Vole Golleri",
    "volleys": "Voleler",
    "weakFoot": "Zayıf ayak",
    "weakFootGoals": "Zayıf Ayak Golleri",
    "winRate": "Galibiyet Oranı",
    "workRateMovement": "Çalışma Oranı ve Hareket",
    "workRateMovementTitle": "Çalışma Oranı ve Hareket",
    "xgPrevented": "önlenen xG",
    "yellowCards": "Sarı Kartlar"
  },
  "history": {
    "active": "Aktif",
    "attacking": "Hücum",
    "awards": "Ödüller",
    "caps": "A Milli",
    "careerDetailedStats": "Detaylı Kariyer İstatistikleri",
    "careerOverview": "Kariyer Özeti",
    "careerStats": "Kariyer İstatistikleri",
    "clubCareer": "Kulüp Kariyeri",
    "clubHistory": "Kulüp Geçmişi",
    "clubStatistics": "Kulüp İstatistikleri",
    "clubTrophies": "Kulüp Kupaları",
    "clubs": "Kulüpler",
    "clubs_plural": "kulüpler",
    "competition": "Müsabaka",
    "competitionHistory": "Müsabaka Geçmişi",
    "competitionStatistics": "Müsabaka İstatistikleri",
    "competitions": "Turnuvalar",
    "continental": "Kıtasal",
    "country": "Ülke",
    "current": "Güncel",
    "decline": "Reddet",
    "defending": "Savunma",
    "details": "Detaylar",
    "domestic": "Yurtiçi",
    "draw": "Beraberlik",
    "draws": "B",
    "elite": "Elit",
    "formHint": "Turuncu işaretler 7.5+ puanları gösterir",
    "formLast10": "Form (Son 10 Maç)",
    "friendliesNote": "Dostluk maçları (resmi istatistiklerde sayılmaz)",
    "goalConversion": "Gol Dönüşümü",
    "goalsAssists": "{goals} Gol / {assists} Asist",
    "goalsConceded": "Yenen Goller",
    "growth": "Gelişim",
    "growthShort": "Büyüme",
    "honors": "Şerefler",
    "intercontinental": "Kıtalararası",
    "international": "Uluslararası",
    "internationalCareer": "Uluslararası Kariyer",
    "leagueStatistics": "Lig İstatistikleri",
    "loss": "Mağlubiyet",
    "losses": "M",
    "lower": "Küme Düşme",
    "matchesDetails": "{played} Maç: {won}G {drawn}B {lost}M",
    "matchesPlayed": "Oynanan Maçlar",
    "matchesShort": "MÇ",
    "mid": "Orta Sıra",
    "nationalTeam": "Milli Takım",
    "nationalTeamTrophies": "Milli Takım Kupaları",
    "noSpecialCharacteristics": "Özel karakteristik yok",
    "noSpecialTraits": "Özel özellik yok",
    "officialMatchesOnly": "Sadece Resmi Maçlar",
    "overall": "Genel",
    "overallCareerTotal": "Toplam Kariyer",
    "overallEvolution": "Genel Puan Gelişimi",
    "overallPerformance": "Genel Performans",
    "overallWinRate": "Toplam Galibiyet Oranı",
    "overview": "Genel Bakış",
    "peak": "Zirve",
    "performanceBySeason": "Sezona Göre Performans",
    "positionHeatmap": "Pozisyon Isı Haritası",
    "pressureSuccess": "Baskı Başarısı",
    "rating": "Puan",
    "ratingColors": "Puan Renkleri",
    "ratingShort": "PUA",
    "record": "Kayıt",
    "season": "Sezon",
    "seasonBySeason": "Sezon Sezon",
    "seasonDetails": "Sezon Detayları",
    "seasonEvents": "Sezon Olayları",
    "seasonNum": "Sezon {num}",
    "seasons": "Sezonlar",
    "stable": "Stabil",
    "top": "Üst",
    "viewCareerStats": "Kariyer İstatistiklerini Görüntüle",
    "viewDetails": "Detayları Görüntüle",
    "win": "Galibiyet",
    "wins": "G",
    "worldCups": "Dünya Turnuvaları",
    "years": "Yıl",
    "youthCareer": "Gençlik Kariyeri",
    "youthClubHistory": "Genç Kulüp Geçmişi"
  },
  "historyExtra": {
    "current": "Güncel",
    "growthShort": "Büyüme",
    "peak": "Zirve"
  },
  "logs": {
    "continentalSummary": {
      "competition": "Müsabaka",
      "title": "KITASAL ÖZET"
    },
    "cupSummary": {
      "country": "Ülke",
      "playerStats": "Oyuncu İstatistikleri",
      "playerTeam": "Oyuncu Takımı",
      "rating": "Puan",
      "result": "Sonuç",
      "title": "YURTİÇİ KUPA ÖZETİ",
      "winner": "Şampiyon"
    },
    "result": {
      "eliminated": "Elendi",
      "finalist": "Finalist",
      "quarterFinalist": "Çeyrek Finalist",
      "roundOf16": "Son 16",
      "semiFinalist": "Yarı Finalist",
      "winner": "Kazanan"
    }
  },
  "stats": {
    "accurateCrosses": "İsabetli Ortalar",
    "accurateLongBalls": "İsabetli Uzun Toplar",
    "accurateThroughBalls": "İsabetli Ara Paslar",
    "aerialDuelsWon": "Kazanılan Hava Mücadeleleri",
    "assists": "Asistler",
    "assistsP90": "Asist/90",
    "attacking": "Hücum",
    "averageRating": "Ortalama Puan",
    "ballRecoveries": "Top Kurtarma",
    "ballRecoveriesInAttack": "Hücumda Top Kurtarma",
    "ballRecoveriesPerGame": "Top Kurtarma/Maç",
    "bigChancesConverted": "Dönüştürülen Büyük Fırsatlar",
    "bigChancesCreated": "Yaratılan Büyük Fırsatlar",
    "bigChancesMissed": "Kaçırılan Büyük Fırsatlar",
    "careerStats": "Kariyer İstatistikleri",
    "cleanSheets": "Gol Yemeden",
    "clearances": "Uzaklaştırmalar",
    "clearancesPerGame": "Uzaklaştırma/Maç",
    "conceded": "Yenen Goller",
    "defending": "Savunma",
    "detailedStats": "Detaylı İstatistikler",
    "discipline": "Disiplin",
    "dribbles": "Driblingler",
    "dribblesP90": "Dribling/90",
    "dribblesSucceeded": "Başarılı Driblingler",
    "dribblesSuccessPercentage": "Dribling Başarı %",
    "dribbling": "Dribling",
    "duelsWon": "Kazanılan İkili Mücadeleler",
    "errorsLeadingToGoal": "Gole Yol Açan Hatalar",
    "errorsLeadingToShot": "Şuta Yol Açan Hatalar",
    "expectedAssists": "Beklenen Asistler (xA)",
    "expectedGoals": "Beklenen Goller (xG)",
    "foulsCommitted": "Yapılan Fauller",
    "foulsDrawn": "Kazanılan Fauller",
    "foulsPerGame": "Faul/Maç",
    "freeKickGoals": "Serbest Vuruş Golleri",
    "gamesAsSubstitute": "Yedek Oynadığı Maçlar",
    "gamesStarted": "Başladığı Maçlar",
    "goal": "Gol",
    "goalConversion": "Gol Dönüşümü",
    "goals": "Goller",
    "goalsFromInsideBox": "Ceza Sahası İçi Goller",
    "goalsFromOutsideBox": "Ceza Sahası Dışı Goller",
    "goalsP90": "Gol/90",
    "goalsPerMatch": "Maç Başı Gol",
    "groundDuelsWon": "Kazanılan Yer Mücadeleleri",
    "headedGoals": "Kafa Golleri",
    "interceptions": "Top Kesme",
    "interceptionsP90": "Top Kesme/90",
    "keyPasses": "Kilit Paslar",
    "keyPassesP90": "Kilit Pas/90",
    "leftFootGoals": "Sol Ayak Golleri",
    "manOfTheMatch": "Maçın Adamı",
    "matchWinRate": "Maç Kazanma Oranı",
    "matches": "Maçlar",
    "matchesDrawn": "Berabere Kalan Maçlar",
    "matchesLost": "Kaybedilen Maçlar",
    "matchesPlayed": "Oynanan Maçlar",
    "matchesWon": "Kazanılan Maçlar",
    "minutesPlayed": "Oynanan Dakikalar",
    "missedShot": "Kaçırılan Şut",
    "offsides": "Ofsaytlar",
    "overview": "Genel Bakış",
    "passAccuracy": "Pas İsabeti",
    "passCompletion": "Pas İsabet Oranı",
    "passes": "Paslar",
    "passesCompleted": "Tamamlanan Paslar",
    "passesInFinalThird": "Son Üçlüde Paslar",
    "passesInOwnHalf": "Kendi Yarısında Paslar",
    "passing": "Pas",
    "passingCreation": "Pas ve Yaratıcılık",
    "penaltiesConceded": "Verilen Penaltılar",
    "penaltiesWon": "Kazanılan Penaltılar",
    "perMatch": "Maç Başı",
    "possession": "Top Kontrolü",
    "possessionLost": "Kaybedilen Toplar",
    "rating": "Ort. Puan",
    "redCards": "Kırmızı Kartlar",
    "redCardsFromSecondYellow": "İkinci Sarıdan Kırmızı",
    "rightFootGoals": "Sağ Ayak Golleri",
    "savePercentage": "Kurtarış %",
    "shooting": "Şut",
    "shots": "Şutlar",
    "shotsBlocked": "Engellenen Şutlar",
    "shotsBlockedByOpponent": "Engellenen Şutlar",
    "shotsBlockedPerGame": "Engellenen Şut/Maç",
    "shotsOffTarget": "İsabetsiz Şutlar",
    "shotsOnTarget": "İsabetli Şutlar",
    "shotsOnTargetPerGame": "İsabetli Şut/Maç",
    "shotsP90": "Şut/90",
    "tackles": "Müdahaleler",
    "tacklesP90": "Müdahale/90",
    "tacklesPerGame": "Müdahale/Maç",
    "teamOfTheWeek": "Haftanın Takımı",
    "total": "Toplam",
    "touches": "Top Temasları",
    "yellowCards": "Sarı Kartlar"
  }
}